LICENSE.txt
MANIFEST.in
README.rst
requirements.txt
setup.cfg
setup.py
scriber/__init__.py
scriber/api.py
scriber/error.py
scriber/http_client.py
scriber/util.py
scriber.egg-info/PKG-INFO
scriber.egg-info/SOURCES.txt
scriber.egg-info/dependency_links.txt
scriber.egg-info/not-zip-safe
scriber.egg-info/top_level.txt
scriber/data/ca-certificates.crt