Metadata-Version: 1.1
Name: scriber
Version: 0.1.3
Summary: Python client API for scriber.io
Home-page: https://github.com/scriber/scriber.py
Author: Josh Braegger
Author-email: rckclmbr@gmail.com
License: Apache 2.0
Platform: UNKNOWN
Classifier: License :: Other/Proprietary License
Classifier: Programming Language :: Python :: 2.6
Classifier: Programming Language :: Python :: 2.7
Classifier: Programming Language :: Python :: 3.3
Classifier: Programming Language :: Python :: 3.4
Classifier: Topic :: System :: Monitoring
